bing_webmaster_tools/__init__.py
bing_webmaster_tools/client.py
bing_webmaster_tools/config.py
bing_webmaster_tools/errors.py
bing_webmaster_tools/models/__init__.py
bing_webmaster_tools/models/base.py
bing_webmaster_tools/models/content_blocking.py
bing_webmaster_tools/models/content_management.py
bing_webmaster_tools/models/crawling.py
bing_webmaster_tools/models/keyword_analysis.py
bing_webmaster_tools/models/link_analysis.py
bing_webmaster_tools/models/regional_settings.py
bing_webmaster_tools/models/site_management.py
bing_webmaster_tools/models/submission.py
bing_webmaster_tools/models/traffic_analysis.py
bing_webmaster_tools/models/url_management.py
bing_webmaster_tools/py.typed
bing_webmaster_tools/retrying.py
bing_webmaster_tools/services/__init__.py
bing_webmaster_tools/services/api_client.py
bing_webmaster_tools/services/content_blocking.py
bing_webmaster_tools/services/content_management.py
bing_webmaster_tools/services/crawling.py
bing_webmaster_tools/services/keyword_analysis.py
bing_webmaster_tools/services/link_analysis.py
bing_webmaster_tools/services/regional_settings.py
bing_webmaster_tools/services/site_management.py
bing_webmaster_tools/services/submission.py
bing_webmaster_tools/services/traffic_analysis.py
bing_webmaster_tools/services/url_management.py
bing_webmaster_tools/utils.py
bing_webmaster_tools-1.2.0.dist-info/LICENSE
bing_webmaster_tools-1.2.0.dist-info/METADATA
bing_webmaster_tools-1.2.0.dist-info/WHEEL
bing_webmaster_tools-1.2.0.dist-info/RECORD
