Metadata-Version: 2.3
Name: bing-webmaster-tools
Version: 1.2.0
Summary: Python wrapper for the Bing Webmaster Tools API
Keywords: bing,webmaster,seo,api,sdk
Author: Ryan Siddle
Author-email: ryan.siddle@merj.com
Requires-Python: >=3.9,<4.0
Classifier: Development Status :: 3 - Alpha
Classifier: Intended Audience :: Developers
Classifier: License :: OSI Approved :: MIT License
Classifier: Programming Language :: Python :: 3
Classifier: Programming Language :: Python :: 3.9
Classifier: Programming Language :: Python :: 3.10
Classifier: Programming Language :: Python :: 3.11
Classifier: Programming Language :: Python :: 3.12
Classifier: Programming Language :: Python :: 3.13
Classifier: Topic :: Internet :: WWW/HTTP
Classifier: Topic :: Software Development :: Libraries :: Python Modules
Requires-Dist: aiohttp (>=3.10.11,<4.0.0)
Requires-Dist: jinja2 (>=3.1.5,<4.0.0)
Requires-Dist: pydantic (>=2.9.2,<3.0.0)
Requires-Dist: pydantic-settings (>=2.6.0,<3.0.0)
Requires-Dist: tenacity (>=9.0.0,<10.0.0)
Project-URL: Homepage, https://github.com/merj/bing-webmaster-tools
Project-URL: Repository, https://github.com/merj/bing-webmaster-tools
